{
 "absolute_value": 0,
 "align_labels_right": 0,
 "creation": "2023-07-15 08:24:24.591016",
 "css": "\n@import url('https://fonts.googleapis.com/css2?family=Averta:wght@400&display=swap');\n\n.print-format {\n    font-size: 12pt;\n}\n.topbar {\n    padding: 5px;\n    display: flex;\n    justify-content: space-between;\n    align-items: center;\n    position: relative;\n    /*margin-bottom:-50px;*/\n}\n\n.logo {\n    margin-right: 10px;\n    margin-bottom: auto;\n}\n\n.logo img {\n    height: auto;\n    width: 200px;\n}\n\n.quotation {\n    font-size: 25px;\n    margin-left: auto;\n    font-family: 'Averta', sans-serif;\n}\n\n.brand {\n    text-align: right;\n    position: relative;\n}\n\n.brand-name {\n    font-weight: bold;\n    font-family: 'Averta', sans-serif;\n    font-size: 14px;\n}\n\n.line {\n    border-top: 1px solid black;\n    margin-top: auto;\n    width: 100%;\n}\n\n.line-bottom {\n    position: absolute;\n    bottom: -10px;\n    left: 0;\n    width: 100%;\n    border: none;\n    border-bottom: 1px solid black;\n}\n\n\n\n    \n    \n    \n    \n    \n    \n  \n \n  \n  .borderless-table th {\n\tbackground-color: #1e90cb;\n\tcolor: white;\n  }\n  \n  .logo img {\n    height: auto;\n    width: 300px;\n}\n    \n    \n    \n    \n    \n    \n\n.signature-img {\n\tbackground: #fff;\n\tborder-radius: 3px;\n\tmargin-top: 5px;\n\tmax-height: 150px;\n}\n\n",
 "custom_format": 1,
 "default_print_language": "en",
 "disabled": 0,
 "doc_type": "Quotation",
 "docstatus": 0,
 "doctype": "Print Format",
 "font_size": 12,
 "format_data": "[{\"fieldname\": \"print_heading_template\", \"fieldtype\": \"Custom HTML\", \"options\": \"<style>\\n    @import url('https://fonts.googleapis.com/css2?family=Averta:wght@400&display=swap');\\n\\n    .topbar {\\n        padding: 5px;\\n        display: flex;\\n        justify-content: space-between;\\n        align-items: center;\\n        position: relative;\\n        /*margin-bottom:-50px;*/\\n    }\\n\\n    .logo {\\n        margin-right: 10px;\\n        margin-bottom: auto;\\n    }\\n\\n    .logo img {\\n        height: auto;\\n        width: 200px;\\n    }\\n\\n    .quotation {\\n        font-size: 25px;\\n        margin-left: auto;\\n        font-family: 'Averta', sans-serif;\\n    }\\n\\n    .brand {\\n        text-align: right;\\n        position: relative;\\n    }\\n\\n    .brand-name {\\n        font-weight: bold;\\n        font-family: 'Averta', sans-serif;\\n        font-size: 14px;\\n    }\\n\\n    .line {\\n        border-top: 1px solid black;\\n        margin-top: auto;\\n        width: 100%;\\n    }\\n\\n    .line-bottom {\\n        position: absolute;\\n        bottom: -10px;\\n        left: 0;\\n        width: 100%;\\n        border: none;\\n        border-bottom: 1px solid black;\\n    }\\n</style>\\n\\n<div class=\\\"topbar\\\">\\n    <div class=\\\"logo\\\">\\n        <img alt=\\\"Logo\\\" src=\\\"/files/loranet.png\\\">\\n    </div>\\n    <div class=\\\"brand\\\">\\n        <div style=\\\"text-align: right;\\\">\\n            <div class=\\\"quotation\\\">QUOTATION</div>\\n        </div>\\n        <div style=\\\"text-align: right;\\\">\\n            <div class=\\\"brand-name\\\">Loranet Technologies PLT</div><br>\\n            <span>60-1 Jalan Pulau Lumut Q, U10/Q<br>\\n            40170 Shah Alam, Selangor</span><br>\\n            <span>Email: sales@loranet.my</span>\\n        </div>\\n    </div>\\n</div>\\n<div>\\n    <hr>\\n</div>\\n<!--<hr class=\\\"line-bottom\\\">-->\\n\"}, {\"fieldtype\": \"Section Break\", \"label\": \"\"}, {\"fieldtype\": \"Column Break\"}, {\"fieldname\": \"_custom_html\", \"print_hide\": 0, \"label\": \"Custom HTML\", \"fieldtype\": \"HTML\", \"options\": \"<!DOCTYPE html>\\n<div>\\n<p style=\\\"color: #a6a5a2\\\">Bill To</p>\\n<strong>{{doc.customer_name}}</strong><br>\\n{{doc.address_display}} \\n{% if doc.contact_person %}Attention to: {{ doc.contact_person }}{% endif -%}\\n</div>\"}, {\"fieldtype\": \"Column Break\"}, {\"fieldtype\": \"Column Break\"}, {\"fieldname\": \"_custom_html\", \"print_hide\": 0, \"label\": \"Custom HTML\", \"fieldtype\": \"HTML\", \"options\": \"<!DOCTYPE html>\\n<div style=\\\"text-align: left;\\\">\\n    <p style=\\\"background-color; black; text-align: left; display: inline-block; border-collapse: collapse;\\\"><b>No. :</b> {{doc.name}}</p><br>\\n<p style=\\\"background-color; black; text-align: left; display: inline-block; border-collapse: collapse;\\\"><b>Date :</b> {{doc.transaction_date}}</p><br>\\n<p style=\\\"text-align: left; display: inline-block;\\\"><b>Valid until : </b>{{doc.valid_till}}</p>\\n</div>\\n\"}, {\"fieldtype\": \"Section Break\", \"label\": \"\"}, {\"fieldtype\": \"Column Break\"}, {\"fieldname\": \"_custom_html\", \"print_hide\": 0, \"label\": \"Custom HTML\", \"fieldtype\": \"HTML\", \"options\": \"<p style=\\\"text-align: left; display: inline-block; border-collapse: collapse;\\\"><b>Re:</b> {{doc.remark}}</p>\\n\"}, {\"fieldtype\": \"Section Break\", \"label\": \"\"}, {\"fieldtype\": \"Column Break\"}, {\"fieldname\": \"_custom_html\", \"print_hide\": 0, \"label\": \"Custom HTML\", \"fieldtype\": \"HTML\", \"options\": \"<style>\\n  body {\\n    font-family: \\\"Calibri\\\", sans-serif;\\n  }\\n\\n  .borderless-table {\\n    border-collapse: collapse;\\n    width: 100%; /* Set table width to 100% */\\n  }\\n\\n  .borderless-table th,\\n  .borderless-table td {\\n    padding: 8px;\\n    border: none; /* Remove borders */\\n    font-size: 13px; /* Set font size */\\n    line-height: 1.5; /* Set line-height */\\n  }\\n\\n  .borderless-table th {\\n    background-color: #1e90cb;\\n    color: white;\\n  }\\n\\n  /* Set font size for all other elements within the table */\\n  .borderless-table td,\\n  .borderless-table th,\\n  .borderless-table p,\\n  .borderless-table small {\\n    font-size: 13px; /* Set font size */\\n  }\\n\\n  @media print {\\n    /* Add any additional CSS rules for printing here */\\n  }\\n</style>\\n\\n<div data-fieldname=\\\"items\\\" data-fieldtype=\\\"Table\\\">\\n  <table class=\\\"borderless-table\\\">\\n    <thead>\\n      <tr>\\n        <th style=\\\"width: 5%\\\" class=\\\"table-sr\\\">No</th>\\n        <th style=\\\"width: 50%\\\" class=\\\"text-left\\\">Description</th>\\n        <th style=\\\"width: 10%\\\" class=\\\"text-center\\\">Quantity</th>\\n        <th style=\\\"width: 15%\\\" class=\\\"text-center\\\">Rate</th>\\n        <th style=\\\"width: 20%\\\" class=\\\"text-center\\\">Amount</th>\\n      </tr>\\n    </thead>\\n    <tbody>\\n      {% for item in doc.items %}\\n      <tr>\\n        <td class=\\\"table-sr\\\">{{ loop.index }}</td>\\n        <td class=\\\"text-left\\\">\\n          {{item.item_name}} {{ item.description }} <!-- Removed <br /> tag here -->\\n        </td>\\n\\n        <td class=\\\"text-center\\\">\\n          <div class=\\\"value\\\">\\n            <small class=\\\"pull-center\\\"></small>\\n            {{ item.qty }}\\n          </div>\\n        </td>\\n\\n        <td class=\\\"text-right\\\">\\n          <div class=\\\"value\\\">{{ item.get_formatted('rate', item) }}</div>\\n        </td>\\n        <td class=\\\"text-right\\\">\\n          <div class=\\\"value\\\">{{ item.get_formatted('base_amount', item) }}</div>\\n        </td>\\n      </tr>\\n      {% endfor %}\\n    </tbody>\\n    <tfoot>\\n      <tr>\\n        <td colspan=\\\"4\\\" style=\\\"text-align: right\\\">\\n          <strong>GRAND TOTAL:</strong>\\n        </td>\\n        <td class=\\\"text-right\\\">\\n          <strong>{{ \\\"RM {:,.2f}\\\".format(doc.grand_total) }}</strong>\\n        </td>\\n      </tr>\\n    </tfoot>\\n  </table>\\n</div>\\n\"}, {\"fieldtype\": \"Section Break\", \"label\": \"\"}, {\"fieldtype\": \"Column Break\"}, {\"fieldname\": \"_custom_html\", \"print_hide\": 0, \"label\": \"Custom HTML\", \"fieldtype\": \"HTML\", \"options\": \"<!DOCTYPE html>\\n<div>\\n<strong>Terms & Conditions</strong><br>\\n{{doc.terms}}<br>\\n\\nPrepared By : {{doc.employee_name}} <br>\\nPosition : {{doc.designation}}<br>\\nContact : {{doc.contact_number}}\\n\\n</div>\"}]",
 "html": "<html>\n\n    <div class=\"topbar\">\n        <div class=\"logo\">\n            <img alt=\"Logo\" src=\"/files/loranet.png\">\n        </div>\n        <div class=\"brand\">\n            <div style=\"text-align: right;\">\n                <div class=\"quotation\">QUOTATION</div>\n            </div>\n            <div style=\"text-align: right;\">\n                <div class=\"brand-name\">Loranet Technologies PLT</div><br>\n                <span>60-1 Jalan Pulau Lumut Q, U10/Q<br>\n                40170 Shah Alam, Selangor</span><br>\n                <span>Email: sales@loranet.my</span>\n            </div>\n        </div>\n    </div>\n    <div>\n        <hr>\n    </div>\n    \n    \n    <div class=\"row section-break  justify-content-end\" data-label=\"\">\n        <div class=\"col-xs-4 column-break\">\n                <div>\n                    <p style=\"color: #a6a5a2\">Bill To</p>\n                    <strong>{{doc.customer_name}}</strong><br>\n                    {{doc.address_display}} <br>\n                    {% if doc.contact_person %}Attention to: {{ doc.contact_person }}{% endif -%}\n                </div>\n            \n        </div>\n\n        <div class=\"col-xs-4 column-break\">\n        \n        </div>\n\n        <div class=\"col-xs-4 column-break\" >\n\n            <div style=\"float: right;\">\n                <div style=\"text-align: left;\">\n                        <p style=\"background-color; black; text-align: left; display: inline-block; border-collapse: collapse;\"><b>No. :</b> {{doc.name}}</p><br>\n                    <p style=\"background-color; black; text-align: left; display: inline-block; border-collapse: collapse;\"><b>Date :</b> {{doc.transaction_date}}</p><br>\n                    <p style=\"text-align: left; display: inline-block;\"><b>Valid until : </b>{{doc.valid_till}}</p>\n                </div>\n            </div>\n            \n        \n        </div>\n\n    </div>\n    \n    <p style=\"text-align: left; display: inline-block; border-collapse: collapse;\"><b>Re:</b> {{doc.remark}}</p>\n\n\n      \n    <div data-fieldname=\"items\" data-fieldtype=\"Table\">\n        <table class=\"borderless-table tabletrans\">\n            <thead>\n                <tr>\n                  <th style=\"width: 5%\" class=\"table-sr\">No</th>\n                  <th style=\"width: 50%\" class=\"text-left\">Description</th>\n                  <th style=\"width: 10%\" class=\"text-center\">Quantity</th>\n                  <th style=\"width: 15%\" class=\"text-center\">Rate</th>\n                  <th style=\"width: 20%\" class=\"text-center\">Amount</th>\n                </tr>\n              </thead>\n            <tbody>\n                {% for item in doc.items %}\n                <tr>\n                  <td class=\"table-sr\">{{ loop.index }}</td>\n                  <td class=\"text-left keep-together\">\n                    {{item.item_name}} {{ item.description }} <!-- Removed <br /> tag here -->\n                  </td>\n          \n                  <td class=\"text-center\">\n                    <div class=\"value\">\n                      <small class=\"pull-center\"></small>\n                      {{ item.qty }}\n                    </div>\n                  </td>\n          \n                  <td class=\"text-right\">\n                    <div class=\"value\">{{ item.get_formatted('rate', item) }}</div>\n                  </td>\n                  <td class=\"text-right\">\n                    <div class=\"value\">{{ item.get_formatted('base_amount', item) }}</div>\n                  </td>\n                </tr>\n                {% endfor %}\n              </tbody>\n            <tfoot>\n                <tr>\n                  <td colspan=\"4\" style=\"text-align: right\">\n                    <strong>GRAND TOTAL:</strong>\n                  </td>\n                  <td class=\"text-right\">\n                    <strong>{{ \"RM {:,.2f}\".format(doc.grand_total) }}</strong>\n                  </td>\n                </tr>\n              </tfoot>\n        </table>\n    </div>\n    \n    \n    <div>\n        <strong>Terms & Conditions</strong><br>\n        {{doc.terms}}<br>\n        \n        Prepared By : {{doc.employee_name}} <br>\n        Position : {{doc.designation}}<br>\n        Contact : {{doc.contact_number}}\n        \n    </div>\n\n    \n    \n    \n</html>",
 "idx": 0,
 "line_breaks": 0,
 "margin_bottom": 15.0,
 "margin_left": 15.0,
 "margin_right": 15.0,
 "margin_top": 15.0,
 "modified": "2023-07-15 19:15:27.474753",
 "modified_by": "Administrator",
 "module": "Loranet Technologies",
 "name": "Quotation - Loranet - 2",
 "owner": "Administrator",
 "page_number": "Bottom Left",
 "print_format_builder": 0,
 "print_format_builder_beta": 0,
 "print_format_type": "Jinja",
 "raw_printing": 0,
 "show_section_headings": 0,
 "standard": "Yes"
}